preparser/DynamicHelper.py
preparser/FileHelper.py
preparser/PreParseHelper.py
preparser/TaskHelper.py
preparser/ToolsHelper.py
preparser/__init__.py
preparser-2.0.8.dist-info/LICENSE
preparser-2.0.8.dist-info/METADATA
preparser-2.0.8.dist-info/WHEEL
preparser-2.0.8.dist-info/top_level.txt
preparser-2.0.8.dist-info/RECORD
