Metadata-Version: 2.2
Name: preparser
Version: 2.0.8
Summary: a slight preparser to help parse webpage content or get request from urls,which supports win, mac and unix.
Home-page: https://github.com/BertramYe/preparser
Author: BertramYe
Author-email: bertramyerik@gmail.com
License: MIT
Keywords: preparser,parser,parse,crawl,webpage,html,api,requests,BeautifulSoup4,BeautifulSoup4,python3,windows,mac,linux
Classifier: Development Status :: 5 - Production/Stable
Classifier: Intended Audience :: Developers
Classifier: Programming Language :: Python :: 3
Classifier: Operating System :: OS Independent
Classifier: License :: OSI Approved :: MIT License
Classifier: Operating System :: Unix
Classifier: Operating System :: MacOS :: MacOS X
Classifier: Operating System :: Microsoft :: Windows
Requires-Python: >=3.9.0
License-File: LICENSE
Requires-Dist: requests
Requires-Dist: beautifulsoup4
Requires-Dist: playwright
Dynamic: author
Dynamic: author-email
Dynamic: classifier
Dynamic: description
Dynamic: description-content-type
Dynamic: home-page
Dynamic: keywords
Dynamic: license
Dynamic: requires-dist
Dynamic: requires-python
Dynamic: summary
